ewha_db_dynamicP/__init__ .py
ewha_db_dynamicP/db_dynamicP.py
ewha_db_dynamicp-0.1.1.dist-info/METADATA
ewha_db_dynamicp-0.1.1.dist-info/WHEEL
ewha_db_dynamicp-0.1.1.dist-info/top_level.txt
ewha_db_dynamicp-0.1.1.dist-info/RECORD
