Metadata-Version: 2.4
Name: ewha_db_dynamicP
Version: 0.1.1
Summary: A database manager for PostgreSQL with trajectory processing.
Author-email: Jiyoon Lee <0197black@gmail.com>
Requires-Python: >=3.8
Requires-Dist: psycopg2-binary
Requires-Dist: pandas
Requires-Dist: geopandas
Requires-Dist: movingpandas
Requires-Dist: tqdm
Requires-Dist: pyyaml
